easycord/__init__.py
easycord/createBot.py
easycord-0.0.1.dist-info/LICENSE.txt
easycord-0.0.1.dist-info/METADATA
easycord-0.0.1.dist-info/WHEEL
easycord-0.0.1.dist-info/top_level.txt
easycord-0.0.1.dist-info/RECORD
